MANIFEST.in
setup.py
changer/__init__.py
changer/c5/__init__.py
changer/c5/blog/__init__.py
changer/c5/blog/admin.py
changer/c5/blog/models.py
changer/c5/blog/tests.py
changer/c5/blog/urls.py
changer/c5/blog/views.py
changer/c5/blog/migrations/0001_initial.py
changer/c5/blog/migrations/__init__.py
changer/c5/blog/templates/blog/base.html
changer/c5/blog/templates/blog/listposts.html
changer/c5/blog/templates/blog/post.html
changer/c5/blog/templates/blog/viewpost.html
changer/c5/emaillogin/__init__.py
changer/c5/example/django.wsgi
changer/c5/example/fabfile.py
changer/c5/example/example/__init__.py
changer/c5/example/example/manage.py
changer/c5/example/example/settings.py
changer/c5/example/example/urls.py
changer/c5/example/example/utils.py
changer/c5/example/example/layout/css/style.css
changer/c5/example/example/layout/css/style.less
changer/c5/example/example/layout/js/less-1.0.41.min.js
changer/c5/example/example/layout/js/modernizr-1.7.min.js
changer/c5/example/example/layout/js/plugins.js
changer/c5/example/example/layout/js/script.js
changer/c5/example/example/main/__init__.py
changer/c5/example/example/main/models.py
changer/c5/example/example/main/tests.py
changer/c5/example/example/main/views.py
changer/c5/example/example/main/templatetags/__init__.py
changer/c5/example/example/serversettings/__init__.py
changer/c5/example/example/serversettings/base.py
changer/c5/example/example/serversettings/local.py
changer/c5/example/example/templates/404.html
changer/c5/example/example/templates/500.html
changer/c5/example/example/templates/base.tmpl
changer/c5/example/example/templates/html.html
changer/c5/example/example/templates/humans.txt
changer/c5/example/example/templates/robots.txt
changer/c5/example/example/templates/site.tmpl
changer/c5/example/example/templates/admin/base_site.html
changer/c5/example/example/templates/includes/login.html
changer/c5/example/logs/access.log
changer/c5/example/logs/debug.log
changer/c5/example/logs/error.log
changer_c5.egg-info/PKG-INFO
changer_c5.egg-info/SOURCES.txt
changer_c5.egg-info/dependency_links.txt
changer_c5.egg-info/not-zip-safe
changer_c5.egg-info/pbr.json
changer_c5.egg-info/requires.txt
changer_c5.egg-info/top_level.txt