Metadata-Version: 1.1
Name: changer-c5
Version: 1.2
Summary: Changer C5 Component Library
Home-page: http://www.changer.nl
Author: Christian Verkerk
Author-email: christianverkerk@gmail.com
License: Private
Platform: OS Independent
Classifier: Development Status :: 5 - Production/Stable
Classifier: Environment :: Web Environment
Classifier: Framework :: Django
Classifier: Intended Audience :: Developers
Classifier: Operating System :: OS Independent
Classifier: Programming Language :: Python
Classifier: Topic :: Internet :: WWW/HTTP :: Dynamic Content
Classifier: Topic :: Software Development
Classifier: Topic :: Software Development :: Libraries :: Application Frameworks
